{
  "data": [
    { "id": 1, "name": "John", "gender": "Male", "salary": 40000, "age": 25 },
    {
      "id": 2,
      "name": "Alice",
      "gender": "Female",
      "salary": 41000,
      "age": 28
    },
    { "id": 3, "name": "Bob", "gender": "Male", "salary": 42000, "age": 32 },
    { "id": 4, "name": "Eva", "gender": "Female", "salary": 43000, "age": 24 },
    { "id": 5, "name": "Mike", "gender": "Male", "salary": 44000, "age": 30 },
    {
      "id": 6,
      "name": "Sarah",
      "gender": "Female",
      "salary": 45000,
      "age": 29
    },
    { "id": 7, "name": "David", "gender": "Male", "salary": 46000, "age": 27 },
    {
      "id": 8,
      "name": "Sophia",
      "gender": "Female",
      "salary": 47000,
      "age": 31
    },
    { "id": 9, "name": "Daniel", "gender": "Male", "salary": 48000, "age": 26 },
    {
      "id": 10,
      "name": "Olivia",
      "gender": "Female",
      "salary": 49000,
      "age": 33
    },
    { "id": 11, "name": "James", "gender": "Male", "salary": 50000, "age": 35 },
    {
      "id": 12,
      "name": "Emma",
      "gender": "Female",
      "salary": 51000,
      "age": 27
    },
    {
      "id": 13,
      "name": "William",
      "gender": "Male",
      "salary": 52000,
      "age": 28
    },
    { "id": 14, "name": "Ava", "gender": "Female", "salary": 53000, "age": 30 },
    { "id": 15, "name": "Liam", "gender": "Male", "salary": 54000, "age": 32 },
    { "id": 16, "name": "Mia", "gender": "Female", "salary": 55000, "age": 29 },
    {
      "id": 17,
      "name": "Benjamin",
      "gender": "Male",
      "salary": 56000,
      "age": 31
    },
    {
      "id": 18,
      "name": "Charlotte",
      "gender": "Female",
      "salary": 57000,
      "age": 34
    },
    { "id": 19, "name": "Henry", "gender": "Male", "salary": 58000, "age": 26 },
    {
      "id": 20,
      "name": "Amelia",
      "gender": "Female",
      "salary": 59000,
      "age": 28
    },
    {
      "id": 21,
      "name": "Alexander",
      "gender": "Male",
      "salary": 60000,
      "age": 33
    },
    {
      "id": 22,
      "name": "Evelyn",
      "gender": "Female",
      "salary": 61000,
      "age": 31
    },
    {
      "id": 23,
      "name": "Michael",
      "gender": "Male",
      "salary": 62000,
      "age": 29
    },
    {
      "id": 24,
      "name": "Abigail",
      "gender": "Female",
      "salary": 63000,
      "age": 27
    },
    {
      "id": 25,
      "name": "Daniel",
      "gender": "Male",
      "salary": 64000,
      "age": 32
    },
    {
      "id": 26,
      "name": "Emily",
      "gender": "Female",
      "salary": 65000,
      "age": 30
    },
    {
      "id": 27,
      "name": "Jackson",
      "gender": "Male",
      "salary": 66000,
      "age": 28
    },
    {
      "id": 28,
      "name": "Harper",
      "gender": "Female",
      "salary": 67000,
      "age": 33
    },
    {
      "id": 29,
      "name": "Sebastian",
      "gender": "Male",
      "salary": 68000,
      "age": 35
    },
    {
      "id": 30,
      "name": "Scarlett",
      "gender": "Female",
      "salary": 69000,
      "age": 27
    },
    { "id": 31, "name": "Ethan", "gender": "Male", "salary": 70000, "age": 30 },
    {
      "id": 32,
      "name": "Lily",
      "gender": "Female",
      "salary": 71000,
      "age": 29
    },
    { "id": 33, "name": "Jack", "gender": "Male", "salary": 72000, "age": 28 },
    {
      "id": 34,
      "name": "Aria",
      "gender": "Female",
      "salary": 73000,
      "age": 31
    },
    { "id": 35, "name": "Noah", "gender": "Male", "salary": 74000, "age": 33 },
    {
      "id": 36,
      "name": "Grace",
      "gender": "Female",
      "salary": 75000,
      "age": 26
    },
    {
      "id": 37,
      "name": "Carter",
      "gender": "Male",
      "salary": 76000,
      "age": 29
    },
    { "id": 38, "name": "Zoe", "gender": "Female", "salary": 77000, "age": 31 },
    {
      "id": 39,
      "name": "Matthew",
      "gender": "Male",
      "salary": 78000,
      "age": 32
    },
    {
      "id": 40,
      "name": "Sofia",
      "gender": "Female",
      "salary": 79000,
      "age": 28
    },
    { "id": 41, "name": "Logan", "gender": "Male", "salary": 80000, "age": 30 },
    {
      "id": 42,
      "name": "Madison",
      "gender": "Female",
      "salary": 81000,
      "age": 29
    },
    {
      "id": 43,
      "name": "Christopher",
      "gender": "Male",
      "salary": 82000,
      "age": 31
    },
    {
      "id": 44,
      "name": "Avery",
      "gender": "Female",
      "salary": 83000,
      "age": 27
    },
    { "id": 45, "name": "Isaac", "gender": "Male", "salary": 84000, "age": 35 }
  ]
}
